setup.cfg
setup.py
pylogic/__init__.py
pylogic/case.py
pylogic/creationals.py
pylogic/decorators.py
pylogic/exceptions.py
pylogic/functions.py
pylogic/knowledge_base.py
pylogic/predicate.py
pylogic.egg-info/PKG-INFO
pylogic.egg-info/SOURCES.txt
pylogic.egg-info/dependency_links.txt
pylogic.egg-info/top_level.txt
test/test_base_operands.py
test/test_case.py
test/test_case_decorator.py
test/test_case_operands.py
test/test_knowledge_base.py
test/test_knowledge_base2.py
test/test_predicate.py
test/test_rule_decorator.py