Metadata-Version: 1.1
Name: pylogic
Version: 0.1.6
Summary: First description for the module
Home-page: https://github.com/fran-bravo/pylogic-module
Author: Francisco Bravo
Author-email: fran_ase@hotmail.com
License: MIT
Download-URL: https://github.com/fran-bravo/pylogic-module/tarball/0.1.6
Keywords: testing,logic
Platform: UNKNOWN
Classifier: Development Status :: 3 - Alpha
